dphox/__init__.py
dphox/demo.py
dphox/device.py
dphox/foundry.py
dphox/geometry.py
dphox/parametric.py
dphox/path.py
dphox/pattern.py
dphox/port.py
dphox/route.py
dphox/transform.py
dphox/typing.py
dphox/utils.py
dphox/prefab/__init__.py
dphox/prefab/active.py
dphox/prefab/passive.py
dphox-0.0.7.dist-info/LICENSE
dphox-0.0.7.dist-info/METADATA
dphox-0.0.7.dist-info/WHEEL
dphox-0.0.7.dist-info/top_level.txt
dphox-0.0.7.dist-info/RECORD
