Metadata-Version: 2.1
Name: dphox
Version: 0.0.7
Summary: UNKNOWN
Home-page: UNKNOWN
License: UNKNOWN
Platform: UNKNOWN
Requires-Dist: numpy (>=1.19)
Requires-Dist: scipy (==1.7.1)
Requires-Dist: shapely (==1.7.1)
Requires-Dist: klamath (>=1.2)
Requires-Dist: networkx (>=2.4)
Provides-Extra: all
Requires-Dist: matplotlib (>=3.4.2) ; extra == 'all'
Requires-Dist: bokeh (==2.2.3) ; extra == 'all'
Requires-Dist: holoviews (==1.14.6) ; extra == 'all'
Requires-Dist: trimesh (==3.9.30) ; extra == 'all'
Requires-Dist: triangle (==20200424) ; extra == 'all'
